setup.py
clear_cache/__init__.py
clear_cache.egg-info/PKG-INFO
clear_cache.egg-info/SOURCES.txt
clear_cache.egg-info/dependency_links.txt
clear_cache.egg-info/top_level.txt